enforce_notebook_run_order/__init__.py
enforce_notebook_run_order/cli.py
enforce_notebook_run_order/enforce_notebook_run_order.py
enforce_notebook_run_order/utils.py
enforce_notebook_run_order-2.1.1.dist-info/METADATA
enforce_notebook_run_order-2.1.1.dist-info/WHEEL
enforce_notebook_run_order-2.1.1.dist-info/entry_points.txt
enforce_notebook_run_order-2.1.1.dist-info/RECORD
