Metadata-Version: 2.1
Name: enforce-notebook-run-order
Version: 2.1.1
Summary: Don't let notebook cells run out of order
License: MIT
Author: Chris Hacker
Author-email: c.m.hacker1997@gmail.com
Requires-Python: >=3.9,<4.0
Classifier: License :: OSI Approved :: MIT License
Classifier: Programming Language :: Python :: 3
Classifier: Programming Language :: Python :: 3.9
Classifier: Programming Language :: Python :: 3.10
Classifier: Programming Language :: Python :: 3.11
Classifier: Programming Language :: Python :: 3.12
Requires-Dist: click (>=8.1.7,<9.0.0)
Requires-Dist: pre-commit (>=3.7.1,<5.0.0)
Requires-Dist: rich (>=14.2.0,<15.0.0)
